fetcha/__init__.py
fetcha/ssb.py
fetcha-0.0.2.dist-info/LICENSE
fetcha-0.0.2.dist-info/METADATA
fetcha-0.0.2.dist-info/WHEEL
fetcha-0.0.2.dist-info/top_level.txt
fetcha-0.0.2.dist-info/RECORD
