Metadata-Version: 2.1
Name: fetcha
Version: 0.0.2
Summary: Talk to SSB using Python.
Home-page: https://github.com/dafeda/fetcha
Author: Feda Curic
Author-email: feda.curic@gmail.com
License: UNKNOWN
Platform: UNKNOWN
Requires-Dist: pyjstat
